AmericoDraws/__init__.py
AmericoDraws/contour_extraction.py
AmericoDraws/image_processor.py
AmericoDraws/path_planning.py
AmericoDraws/utils.py
AmericoDraws/visualization.py
americodraws-0.1.5.dist-info/licenses/LICENSE.txt
americodraws-0.1.5.dist-info/METADATA
americodraws-0.1.5.dist-info/WHEEL
americodraws-0.1.5.dist-info/top_level.txt
americodraws-0.1.5.dist-info/RECORD
