Metadata-Version: 2.4
Name: AmericoDraws
Version: 0.1.5
Summary: Convert images into 3D drawing paths suitable for robotic arms.
Home-page: https://github.com/lucasddoliveira/AmericoDraws
Author: Lucas Dantas
Author-email: Lucas Dantas de Oliveira <lucasddoliveira1@gmail.com>
License: MIT
Project-URL: Homepage, https://github.com/lucasddoliveira/AmericoDraws
Project-URL: Bug Tracker, https://github.com/lucasddoliveira/AmericoDraws/issues
Classifier: Programming Language :: Python :: 3
Classifier: License :: OSI Approved :: MIT License
Classifier: Operating System :: OS Independent
Requires-Python: >=3.7
License-File: LICENSE.txt
Requires-Dist: numpy>=1.19.0
Requires-Dist: matplotlib>=3.3.0
Requires-Dist: opencv-python>=4.5.0
Requires-Dist: Pillow>=8.0.0
Requires-Dist: scikit-learn>=0.24.0
Requires-Dist: networkx>=2.5.0
Requires-Dist: rembg>=2.0.0
Dynamic: author
Dynamic: home-page
Dynamic: license-file
Dynamic: requires-python
